fw_gear_rtp2_pipeline/__init__.py
fw_gear_rtp2_pipeline/main.py
fw_gear_rtp2_pipeline/parser.py
fw_gear_rtp2_pipeline/utils.py
fw_gear_rtp2_pipeline-0.2.3.dist-info/LICENSE
fw_gear_rtp2_pipeline-0.2.3.dist-info/METADATA
fw_gear_rtp2_pipeline-0.2.3.dist-info/WHEEL
fw_gear_rtp2_pipeline-0.2.3.dist-info/RECORD
