Metadata-Version: 2.1
Name: fw-gear-rtp2-pipeline
Version: 0.2.3
Summary: Tract and metrics generation for  Diffusion MRI
Home-page: https://gitlab.com/flywheel-io/scientific-solutions/gears/rtp2-pipeline
License: MIT
Keywords: Flywheel,Gears
Author: Flywheel
Author-email: support@flywheel.io
Requires-Python: >=3.8,<4.0
Classifier: License :: OSI Approved :: MIT License
Classifier: Programming Language :: Python :: 3
Classifier: Programming Language :: Python :: 3.8
Classifier: Programming Language :: Python :: 3.9
Classifier: Programming Language :: Python :: 3.10
Classifier: Programming Language :: Python :: 3.11
Classifier: Programming Language :: Python :: 3.12
Classifier: Topic :: Scientific/Engineering
Requires-Dist: Pillow (>=9.2.0,<10.0.0)
Requires-Dist: backoff (>=2.1.2,<3.0.0)
Requires-Dist: flywheel-gear-toolkit (>=0.6,<0.7)
Requires-Dist: flywheel-sdk (>=16.10.12,<17.0.0)
Requires-Dist: nibabel (>=5.1.0,<6.0.0)
Requires-Dist: packaging (>=24.1,<25.0)
Requires-Dist: pandas (>=2.0.1,<3.0.0)
Project-URL: Repository, https://gitlab.com/flywheel-io/scientific-solutions/gears/rtp2-pipeline
